[
    {
        "file": "D:/pycharm/admin_billdesk/resources\\CAB_RECEIP.pdf",
        "ocr_text": "Booking History\nrapido Ashwini\nCustomer Name Ride ID\nRD17506969273550314\nDriver name\nVehicle Number\nKA07B5736\nMode of Vehicle\nCar\nTime of Ride\nJun 23rd 2025,7:30 PM\nSelected Price 3 210\nSSC Block; Tesco HSC, Tesco Campus Rd; Nallurhalli; Whitefield, Bengaluru, Karnataka 0 560066, India\n96, Tulsi Theater Rd, Manjunatha Layout; Marathahalli Village, Marathahalli; Bengaluru; Karnataka 560037, India\nThis document is issued on request by the passenger Rapido does nor collect any feercommission from passengers and shall not issue tax invoices IO the passengers under this segment. The document may be used for all official reimbursement plrposes_\n#Selected Price refers t0 the initial price decided between User and Drivers from the estimated price range\nprasad",
        "extracted_fields": {
            "provider": "Rapido",
            "ride_id": "RD17506969273550314",
            "date": "Jun 23rd 2025",
            "time": "7:30 PM",
            "total_amount": 210,
            "currency": "INR",
            "pickup_address": "SSC Block; Tesco HSC, Tesco Campus Rd; Nallurhalli; Whitefield, Bengaluru, Karnataka 0 560066, India",
            "dropoff_address": "96, Tulsi Theater Rd, Manjunatha Layout; Marathahalli Village, Marathahalli; Bengaluru; Karnataka 560037, India",
            "vehicle_number": "KA07B5736"
        }
    },
    {
        "file": "D:/pycharm/admin_billdesk/resources\\CAB_RECEIPT_RD17506969273550314.pdf",
        "ocr_text": "Booking History\nCustomer Name Ride ID\nrapido Ashwini\nRD17506969273550314\nDriver name\nprasad KA07B5736\nVehicle Number\nMode of Vehicle\nCar\nTime of Ride\nJun 23rd 2025,10.17 PM\nSelected Price 3210\nGate 1, Forum Shantiniketan Mall,FORUM SHANTINIKETAN MALL, PRESTIGE SHANTINIKETAN, Whitefield Main Rd, Thigalarapalya, Krishnarajapuram, Bengaluru, Karnataka 560067, India\n96, Tulsi Theater Rd, Manjunatha Layout, Marathahalli Village, Marathahalli; Bengaluru, Karnataka 560037, India\nThis document is issued on request by the passenger: Rapido does not collect any feelcommission from passengers and shall not issue tax invoices to the passengers under this segment: The document may be used for all official reimbursement purposes\n#Selected Price refers to the initial price decided between User and Drivers from the estimated price range",
        "extracted_fields": {
            "provider": "Rapido",
            "ride_id": "RD17506969273550314",
            "date": "Jun 23rd 2025",
            "time": "10.17 PM",
            "total_amount": 3210,
            "currency": null,
            "pickup_address": "Gate 1, Forum Shantiniketan Mall,FORUM SHANTINIKETAN MALL, PRESTIGE SHANTINIKETAN, Whitefield Main Rd, Thigalarapalya, Krishnarajapuram, Bengaluru, Karnataka 560067, India",
            "dropoff_address": "96, Tulsi Theater Rd, Manjunatha Layout, Marathahalli Village, Marathahalli; Bengaluru, Karnataka 560037, India",
            "vehicle_number": "KA07B5736"
        }
    },
    {
        "file": "D:/pycharm/admin_billdesk/resources\\receipt_9ed71f8b-428d-4d31-8743-c3dda2c2e686.pdf",
        "ocr_text": "Uber\nOctober 9, 2025\nHere's your receipt for your ride, Ashwini\nWe hope you enjoyed your ride this afternoon.\nTotal\n{123.02\nSuggested fare\n<126.82\nSubtotal\n{126.82\nPromotion\n33.80\nPayments\n0\nCash 10/9/25 3.05 PM\n{123.02\nThis receipt reflects the Suggested Fare (excluding GST) and is not a tax invoice, but can be used for official reimbursement purposes_ No GST is being recovered by Uber from the riders on this Trip.\nYou rode with Murali\nLicense Plate: KA4OB167O\nAuto 7.11 kilometers 27 minutes\n2.37 PM 5, Nallurhalli; Whitefield, Bengaluru; Karnataka 560066, India\n3.04 PM XM2X+RAW, Tulsi Theater Rd, Kaveri Layout; Marathahalli Village, Marathahalli;, Bengaluru; Karnataka 560037 , India",
        "extracted_fields": {
            "provider": "Uber",
            "ride_id": null,
            "date": "October 9, 2025",
            "time": null,
            "total_amount": 123.02,
            "currency": null,
            "pickup_address": "5, Nallurhalli; Whitefield, Bengaluru; Karnataka 560066, India",
            "dropoff_address": "XM2X+RAW, Tulsi Theater Rd, Kaveri Layout; Marathahalli Village, Marathahalli;, Bengaluru; Karnataka 560037 , India",
            "vehicle_number": "KA4OB167O"
        }
    }
]